MANIFEST.in
README.md
setup.cfg
setup.py
caddy/__init__.py
caddy/main.py
caddy.egg-info/PKG-INFO
caddy.egg-info/SOURCES.txt
caddy.egg-info/dependency_links.txt
caddy.egg-info/entry_points.txt
caddy.egg-info/top_level.txt
caddy/cli/__init__.py
caddy/cli/processor.py
caddy/cli/test_processor.py
caddy/cli/lang/__init__.py
caddy/cli/lang/parser.py
caddy/cli/lang/points.py
caddy/cli/lang/test_parser.py
caddy/cli/lang/test_points.py
caddy/cli/parsing/__init__.py
caddy/cli/parsing/combinator.py
caddy/cli/parsing/parsers.py
caddy/cli/parsing/result.py
caddy/cli/parsing/test_combinator.py
caddy/cli/parsing/test_parsers.py
caddy/cli/parsing/test_result.py
caddy/model/__init__.py
caddy/model/actions.py
caddy/model/circle.py
caddy/model/model.py
caddy/model/model_interface.py
caddy/model/polyline.py
caddy/model/rectangle.py
caddy/model/shape.py
caddy/model/tests/__init__.py
caddy/model/tests/test_actions.py
caddy/model/tests/test_circle.py
caddy/model/tests/test_id_generator.py
caddy/model/tests/test_model.py
caddy/model/tests/test_model_interface.py
caddy/model/tests/test_model_observer.py
caddy/model/tests/test_poyline.py
caddy/model/tests/test_rectangle.py
caddy/model/tests/test_shape.py
caddy/presenter/__init__.py
caddy/presenter/file_reader.py
caddy/presenter/file_writer.py
caddy/presenter/presenter.py
caddy/presenter/tool_context.py
caddy/presenter/tests/__init__.py
caddy/presenter/tests/test_drawing_visitor.py
caddy/presenter/tests/test_file_reader.py
caddy/presenter/tests/test_file_writer.py
caddy/presenter/tests/test_persistence_visitor.py
caddy/presenter/tests/test_presenter.py
caddy/presenter/tests/test_tool.py
caddy/presenter/tool/__init__.py
caddy/presenter/tool/base_tool.py
caddy/presenter/tool/circle_tool.py
caddy/presenter/tool/default_tool.py
caddy/presenter/tool/eraser_tool.py
caddy/presenter/tool/line_tool.py
caddy/presenter/tool/list_tool.py
caddy/presenter/tool/move_tool.py
caddy/presenter/tool/rectangle_tool.py
caddy/presenter/visitor/__init__.py
caddy/presenter/visitor/drawing_visitor.py
caddy/presenter/visitor/persistence_visitor.py
caddy/shared/__init__.py
caddy/shared/command_interface.py
