Metadata-Version: 2.1
Name: caddy
Version: 1.3.2
Summary: Semester project for OOP course
Home-page: https://gitlab.fit.cvut.cz/jezekra1/oop-semester-project
Author: Radek Ježek, Dominika Králiková, Róbert Selvek, Jakub Topič
Author-email: topicjak@fit.cvut.cz
License: UNKNOWN
Platform: UNKNOWN
Classifier: Operating System :: OS Independent
Classifier: Programming Language :: Python
Classifier: License :: OSI Approved :: MIT License
Classifier: Topic :: Utilities
